hwrk/__init__.py
hwrk/main.py
hwrk-0.3.dist-info/METADATA
hwrk-0.3.dist-info/WHEEL
hwrk-0.3.dist-info/entry_points.txt
hwrk-0.3.dist-info/top_level.txt
hwrk-0.3.dist-info/RECORD
