Metadata-Version: 2.1
Name: hwrk
Version: 0.3
Summary: simple script to not forget about your homework
Home-page: https://gitlab.com/GrgBls/hwrk
Author: GrgBls
Author-email: UNKNOWN
License: UNKNOWN
Platform: UNKNOWN
